goldieseeker/GusherMap.py
goldieseeker/GusherNode.py
goldieseeker/__init__.py
goldieseeker/__main__.py
goldieseeker/strats.py
goldieseeker/images/ap.png
goldieseeker/images/lo.png
goldieseeker/images/mb.png
goldieseeker/images/sg.png
goldieseeker/images/ss.png
goldieseeker/maps/ap/connections.txt
goldieseeker/maps/ap/distance_modifiers.txt
goldieseeker/maps/ap/gushers.csv
goldieseeker/maps/ap/weights.txt
goldieseeker/maps/lo/connections.txt
goldieseeker/maps/lo/distance_modifiers.txt
goldieseeker/maps/lo/gushers.csv
goldieseeker/maps/lo/weights.txt
goldieseeker/maps/mb/connections.txt
goldieseeker/maps/mb/distance_modifiers.txt
goldieseeker/maps/mb/gushers.csv
goldieseeker/maps/mb/weights.txt
goldieseeker/maps/sg/connections.txt
goldieseeker/maps/sg/distance_modifiers.txt
goldieseeker/maps/sg/gushers.csv
goldieseeker/maps/sg/weights.txt
goldieseeker/maps/ss/connections.txt
goldieseeker/maps/ss/distance_modifiers.txt
goldieseeker/maps/ss/gushers.csv
goldieseeker/maps/ss/weights.txt
goldieseeker-1.0.dist-info/LICENSE.txt
goldieseeker-1.0.dist-info/METADATA
goldieseeker-1.0.dist-info/WHEEL
goldieseeker-1.0.dist-info/entry_points.txt
goldieseeker-1.0.dist-info/top_level.txt
goldieseeker-1.0.dist-info/RECORD
