Metadata-Version: 2.1
Name: goldieseeker
Version: 1.0
Summary: A command-line tool for generating and evaluating Goldie Seeking strategies
Home-page: https://github.com/redoxwarfare/goldieseeker
Author: redoxwarfare
License: MIT
Platform: UNKNOWN
Classifier: Programming Language :: Python :: 3
Classifier: License :: OSI Approved :: MIT License
Classifier: Development Status :: 4 - Beta
Requires-Python: >=3.6
Requires-Dist: click
Requires-Dist: networkx
Requires-Dist: matplotlib
Requires-Dist: numpy
Requires-Dist: scipy
Requires-Dist: pyparsing
